{
  "type": "FeatureCollection", 
  "features": [
    {
      "geometry": {
        "type": "Polygon", 
        "coordinates": [
          [
            [
              -67.388, 
              -35.999
            ], 
            [
              -67.388, 
              -31.868
            ], 
            [
              -64.881, 
              -31.868
            ], 
            [
              -64.881, 
              -35.999
            ], 
            [
              -67.388, 
              -35.999
            ]
          ]
        ]
      }, 
      "type": "Feature", 
      "properties": {
        "lang": "ENG", 
        "woeid": 56043548, 
        "name": "America/Argentina/San_Luis", 
        "ne_latitude": -31.868, 
        "provider": "geoplanet 7.6.0", 
        "ne_longitude": -64.881, 
        "longitude": -66.134, 
        "placetype": "Timezone", 
        "iso": "AR", 
        "date_indexed": "2010-12-02T17:42:05Z", 
        "parent_woeid": 23424747, 
        "latitude": -33.934, 
        "sw_longitude": -67.388, 
        "fullname": "America/Argentina/San_Luis, Argentina", 
        "sw_latitude": -35.999
      }, 
      "id": 56043548
    }
  ]
}